{
  "lastCheckedAt": "2026-03-13T22:12:46.574Z",
  "lastNotifiedVersion": "2026.3.8",
  "lastNotifiedTag": "latest",
  "autoInstallId": "68a5e54d-0ce7-4ef4-9c36-b78c3f9619d9",
  "lastAvailableVersion": "2026.3.12",
  "lastAvailableTag": "latest",
  "autoFirstSeenVersion": "2026.3.12",
  "autoFirstSeenTag": "latest",
  "autoFirstSeenAt": "2026-03-13T14:36:05.273Z",
  "autoLastAttemptVersion": "2026.3.11",
  "autoLastAttemptAt": "2026-03-12T18:18:13.427Z",
  "autoLastSuccessVersion": "2026.3.11",
  "autoLastSuccessAt": "2026-03-12T18:18:13.427Z"
}
